{"type":"PR","pr":{"number":201,"head":"2462e3ac0bd377692df12bd9005bb853d64176d2"},"user":"Radmila.ZHIVKOVA","status":"draft","branch":"cms/cef-building-blocks","collection":"stands","title":"CEF Building Blocks","description":"No Description!","objects":{"entry":{"path":"data/stands/cef-building-blocks.md","sha":"f4b7ebd00849b7ba2f8414d844ad26db06ea969d"},"files":[{"path":"/static/img/connectingeurope.png","sha":"a17d743286c83f2028105ff62fb0663ec7dbd606"}]},"timeStamp":"2018-09-21T09:29:19.619Z"}