{"type":"PR","pr":{"number":401,"head":"f1a33fcfc7181fac39ae5052924b45ec55efe741"},"user":"Radmila.ZHIVKOVA","status":"pending_publish","branch":"cms/markus-foti","collection":"speakers","title":"Senior Expert - eTranslation at DG Translation","description":"No Description!","objects":{"entry":{"path":"data/speakers/markus-foti.md","sha":"fa23d6de07e3117154e88f76110d9ba3c6e50387"},"files":[{"path":"/static/img/markus-foti.png.jpg","sha":"bae5ac2dd2fc756f3bf69d5365518520de4b79bd"}]},"timeStamp":"2018-11-09T10:45:27.343Z"}